network3_medusa/.gitignore
network3_medusa/__init__.py
network3_medusa/network3_medusa.py
network3_medusa/script.py
network3_medusa/sent_to_hedera.j2
network3_medusa-1.1.0.dist-info/entry_points.txt
network3_medusa-1.1.0.dist-info/WHEEL
network3_medusa-1.1.0.dist-info/METADATA
network3_medusa-1.1.0.dist-info/RECORD
